edprompt/__init__.py
edprompt/edprompt.py
edprompt-0.0.10.dist-info/LICENSE
edprompt-0.0.10.dist-info/METADATA
edprompt-0.0.10.dist-info/WHEEL
edprompt-0.0.10.dist-info/top_level.txt
edprompt-0.0.10.dist-info/RECORD
