Metadata-Version: 2.1
Name: edprompt
Version: 0.0.10
Summary: python shell prompt cli editor joke saver prompt bloody hell lmao 🤣🤣🤣
Home-page: https://github.com/FarAway6834/edprompt
Author: du7ec
Author-email: dutec6834@gmail.com
Keywords: python,shell,prompt,cli,editer,jokesaver,edprompt
Classifier: Programming Language :: Python :: 3.6
Classifier: Programming Language :: Python :: 3.7
Classifier: Programming Language :: Python :: 3.8
Classifier: Programming Language :: Python :: 3.9
Classifier: Programming Language :: Python :: 3.10
Classifier: Programming Language :: Python :: 3.11
Classifier: Programming Language :: Python :: 3.12
Classifier: Programming Language :: Python :: 3.13
Classifier: Programming Language :: Python :: 3.14
Requires-Python: >=3.6
License-File: LICENSE
Requires-Dist: clro
